odoo9_addon_website_sale_checkout_skip_payment-9.0.1.0.1-py2.7-nspkg.pth
odoo9_addon_website_sale_checkout_skip_payment-9.0.1.0.1.dist-info/DESCRIPTION.rst
odoo9_addon_website_sale_checkout_skip_payment-9.0.1.0.1.dist-info/METADATA
odoo9_addon_website_sale_checkout_skip_payment-9.0.1.0.1.dist-info/RECORD
odoo9_addon_website_sale_checkout_skip_payment-9.0.1.0.1.dist-info/WHEEL
odoo9_addon_website_sale_checkout_skip_payment-9.0.1.0.1.dist-info/metadata.json
odoo9_addon_website_sale_checkout_skip_payment-9.0.1.0.1.dist-info/namespace_packages.txt
odoo9_addon_website_sale_checkout_skip_payment-9.0.1.0.1.dist-info/top_level.txt
odoo_addons/website_sale_checkout_skip_payment/README.rst
odoo_addons/website_sale_checkout_skip_payment/__init__.py
odoo_addons/website_sale_checkout_skip_payment/__openerp__.py
odoo_addons/website_sale_checkout_skip_payment/controllers/__init__.py
odoo_addons/website_sale_checkout_skip_payment/controllers/main.py
odoo_addons/website_sale_checkout_skip_payment/i18n/am.po
odoo_addons/website_sale_checkout_skip_payment/i18n/ar.po
odoo_addons/website_sale_checkout_skip_payment/i18n/bg.po
odoo_addons/website_sale_checkout_skip_payment/i18n/bs.po
odoo_addons/website_sale_checkout_skip_payment/i18n/ca.po
odoo_addons/website_sale_checkout_skip_payment/i18n/cs.po
odoo_addons/website_sale_checkout_skip_payment/i18n/da.po
odoo_addons/website_sale_checkout_skip_payment/i18n/de.po
odoo_addons/website_sale_checkout_skip_payment/i18n/el_GR.po
odoo_addons/website_sale_checkout_skip_payment/i18n/en_GB.po
odoo_addons/website_sale_checkout_skip_payment/i18n/es.po
odoo_addons/website_sale_checkout_skip_payment/i18n/es_AR.po
odoo_addons/website_sale_checkout_skip_payment/i18n/es_CL.po
odoo_addons/website_sale_checkout_skip_payment/i18n/es_CO.po
odoo_addons/website_sale_checkout_skip_payment/i18n/es_CR.po
odoo_addons/website_sale_checkout_skip_payment/i18n/es_DO.po
odoo_addons/website_sale_checkout_skip_payment/i18n/es_EC.po
odoo_addons/website_sale_checkout_skip_payment/i18n/es_MX.po
odoo_addons/website_sale_checkout_skip_payment/i18n/es_PE.po
odoo_addons/website_sale_checkout_skip_payment/i18n/es_VE.po
odoo_addons/website_sale_checkout_skip_payment/i18n/et.po
odoo_addons/website_sale_checkout_skip_payment/i18n/eu.po
odoo_addons/website_sale_checkout_skip_payment/i18n/fa.po
odoo_addons/website_sale_checkout_skip_payment/i18n/fi.po
odoo_addons/website_sale_checkout_skip_payment/i18n/fr.po
odoo_addons/website_sale_checkout_skip_payment/i18n/fr_CA.po
