Metadata-Version: 2.0
Name: odoo9-addon-website-sale-checkout-skip-payment
Version: 9.0.1.0.1
Summary: Skip payment for logged users in checkout process
Home-page: https://www.tecnativa.com
Author: Tecnativa, Odoo Community Association (OCA)
Author-email: support@odoo-community.org
License: LGPL-3
Platform: UNKNOWN
Classifier: Programming Language :: Python
Classifier: Framework :: Odoo
Classifier: License :: OSI Approved :: GNU Lesser General Public License v3 (LGPLv3)
Requires-Python: ~=2.7
Requires-Dist: odoo (<9.1a,>=9.0a)
